fluxlate/__init__.py
fluxlate/main.py
fluxlate-0.1.0.dist-info/METADATA
fluxlate-0.1.0.dist-info/WHEEL
fluxlate-0.1.0.dist-info/entry_points.txt
fluxlate-0.1.0.dist-info/licenses/LICENSE
fluxlate-0.1.0.dist-info/RECORD
