Metadata-Version: 2.4
Name: fluxlate
Version: 0.1.0
Summary: Translate .po files using local LLMs via Ollama
Project-URL: Homepage, https://github.com/ereli/Fluxlate
Project-URL: Repository, https://github.com/ereli/Fluxlate
Author-email: Ereli <ereli@example.com>
License: MIT
License-File: LICENSE
Keywords: i18n,llm,ollama,po-file,translation
Requires-Python: >=3.11
Requires-Dist: ollama>=0.6.1
Requires-Dist: polib>=1.2.0
Requires-Dist: tqdm>=4.67.1
Requires-Dist: typer>=0.21.0
